{"timeCards":[{"monthDay":"17 ИЮЛ","weekDay":"ПН","dayStartTime":"7:53","breaks":[{"breakStartTime":"8:10","breakEndTime":"8:16","breakTimeTotal":"5 м "},{"breakStartTime":"12:42","breakEndTime":"12:52","breakTimeTotal":"9 м "}],"dayEndTime":"16:15","dayWorkTimeTotal":"8 ч 7 м "},{"monthDay":"18 ИЮЛ","weekDay":"ВТ","dayStartTime":"7:30","breaks":[{"breakStartTime":"7:45","breakEndTime":"7:54","breakTimeTotal":"9 м "},{"breakStartTime":"12:03","breakEndTime":"12:16","breakTimeTotal":"13 м "}],"dayEndTime":"15:56","dayWorkTimeTotal":"8 ч 4 м "},{"monthDay":"19 ИЮЛ","weekDay":"СР","dayStartTime":"7:09","breaks":[{"breakStartTime":"7:24","breakEndTime":"7:34","breakTimeTotal":"10 м "},{"breakStartTime":"15:38","breakEndTime":"15:47","breakTimeTotal":"9 м "}],"dayEndTime":"16:05","dayWorkTimeTotal":"8 ч 36 м "},{"monthDay":"20 ИЮЛ","weekDay":"ЧТ","dayStartTime":"7:35","breaks":[{"breakStartTime":"8:17","breakEndTime":"8:24","breakTimeTotal":"7 м "},{"breakStartTime":"12:25","breakEndTime":"12:32","breakTimeTotal":"7 м "}],"dayEndTime":"16:08","dayWorkTimeTotal":"8 ч 19 м "},{"monthDay":"21 ИЮЛ","weekDay":"ПТ","dayStartTime":"7:37","breaks":[{"breakStartTime":"7:48","breakEndTime":"7:57","breakTimeTotal":"9 м "},{"breakStartTime":"12:54","breakEndTime":"13:14","breakTimeTotal":"20 м "}],"dayEndTime":"16:08","dayWorkTimeTotal":"8 ч 1 м "},{"monthDay":"22 ИЮЛ","weekDay":"СБ","dayStartTime":"12:56","dayEndTime":"14:54","dayWorkTimeTotal":"1 ч 57 м "},{"monthDay":"24 ИЮЛ","weekDay":"ПН","dayStartTime":"7:36","breaks":[{"breakStartTime":"8:24","breakEndTime":"8:33","breakTimeTotal":"9 м "},{"breakStartTime":"12:18","breakEndTime":"12:27","breakTimeTotal":"9 м "}],"dayEndTime":"16:05","dayWorkTimeTotal":"8 ч 11 м "},{"monthDay":"25 ИЮЛ","weekDay":"ВТ","dayStartTime":"7:58","breaks":[{"breakStartTime":"8:08","breakEndTime":"8:17","breakTimeTotal":"9 м "},{"breakStartTime":"12:12","breakEndTime":"12:31","breakTimeTotal":"19 м "}],"dayEndTime":"16:14","dayWorkTimeTotal":"7 ч 48 м "},{"monthDay":"26 ИЮЛ","weekDay":"СР","dayStartTime":"7:56","breaks":[{"breakStartTime":"8:12","breakEndTime":"8:19","breakTimeTotal":"7 м "},{"breakStartTime":"12:14","breakEndTime":"12:22","breakTimeTotal":"8 м "}],"dayEndTime":"16:15","dayWorkTimeTotal":"8 ч 3 м "},{"monthDay":"27 ИЮЛ","weekDay":"ЧТ","dayStartTime":"7:31","breaks":[{"breakStartTime":"7:40","breakEndTime":"7:49","breakTimeTotal":"9 м "},{"breakStartTime":"11:47","breakEndTime":"11:57","breakTimeTotal":"10 м "}],"dayEndTime":"15:56","dayWorkTimeTotal":"8 ч 6 м "},{"monthDay":"28 ИЮЛ","weekDay":"ПТ","dayStartTime":"7:57","breaks":[{"breakStartTime":"8:07","breakEndTime":"8:17","breakTimeTotal":"10 м "},{"breakStartTime":"12:25","breakEndTime":"12:35","breakTimeTotal":"10 м "}],"dayEndTime":"16:39","dayWorkTimeTotal":"8 ч 22 м "},{"monthDay":"31 ИЮЛ","weekDay":"ПН","dayStartTime":"8:03","breaks":[{"breakStartTime":"8:16","breakEndTime":"8:22","breakTimeTotal":"6 м "},{"breakStartTime":"12:16","breakEndTime":"12:24","breakTimeTotal":"8 м "}],"dayEndTime":"15:39","dayWorkTimeTotal":"7 ч 22 м "},{"monthDay":"1 АВГ","weekDay":"ВТ","dayStartTime":"7:31","breaks":[{"breakStartTime":"7:44","breakEndTime":"7:55","breakTimeTotal":"11 м "},{"breakStartTime":"12:08","breakEndTime":"12:19","breakTimeTotal":"11 м "}],"dayEndTime":"16:09","dayWorkTimeTotal":"8 ч 16 м "},{"monthDay":"2 АВГ","weekDay":"СР","dayStartTime":"8:03","breaks":[{"breakStartTime":"8:12","breakEndTime":"8:22","breakTimeTotal":"10 м "},{"breakStartTime":"12:25","breakEndTime":"12:33","breakTimeTotal":"8 м "}],"dayEndTime":"16:21","dayWorkTimeTotal":"7 ч 59 м "},{"monthDay":"3 АВГ","weekDay":"ЧТ","dayStartTime":"7:47","breaks":[{"breakEndTime":"8:13","breakTimeTotal":"10 м "},{"breakStartTime":"11:53","breakEndTime":"12:04","breakTimeTotal":"11 м "}],"dayEndTime":"16:24","dayWorkTimeTotal":"8 ч 16 м "},{"monthDay":"4 АВГ","weekDay":"ПТ","dayStartTime":"7:36","breaks":[{"breakStartTime":"7:43","breakEndTime":"7:52","breakTimeTotal":"9 м "},{"breakStartTime":"12:07","breakEndTime":"12:16","breakTimeTotal":"9 м "}],"dayEndTime":"16:11","dayWorkTimeTotal":"8 ч 17 м "},{"monthDay":"7 АВГ","weekDay":"ПН","dayStartTime":"6:59","breaks":[{"breakStartTime":"7:32","breakEndTime":"7:39","breakTimeTotal":"7 м "},{"breakStartTime":"12:27","breakEndTime":"12:33","breakTimeTotal":"6 м "}],"dayEndTime":"15:45","dayWorkTimeTotal":"8 ч 33 м "},{"monthDay":"8 АВГ","weekDay":"ВТ","dayStartTime":"7:21","breaks":[{"breakStartTime":"7:31","breakEndTime":"7:41","breakTimeTotal":"10 м "},{"breakStartTime":"12:23","breakEndTime":"12:29","breakTimeTotal":"6 м "}],"dayEndTime":"16:11","dayWorkTimeTotal":"8 ч 35 м "},{"monthDay":"9 АВГ","weekDay":"СР","dayStartTime":"7:32","breaks":[{"breakStartTime":"7:41","breakEndTime":"7:51","breakTimeTotal":"10 м "},{"breakStartTime":"12:02","breakEndTime":"12:09","breakTimeTotal":"7 м "}],"dayEndTime":"15:57","dayWorkTimeTotal":"8 ч 8 м "},{"monthDay":"10 АВГ","weekDay":"ЧТ","dayStartTime":"7:55","breaks":[{"breakStartTime":"8:04","breakEndTime":"8:14","breakTimeTotal":"10 м "},{"breakStartTime":"12:11","breakEndTime":"12:19","breakTimeTotal":"8 м "}],"dayEndTime":"16:04","dayWorkTimeTotal":"7 ч 51 м "},{"monthDay":"11 АВГ","weekDay":"ПТ","dayStartTime":"7:54","breaks":[{"breakStartTime":"8:07","breakEndTime":"8:15","breakTimeTotal":"8 м "},{"breakStartTime":"12:38","breakEndTime":"12:44","breakTimeTotal":"6 м "}],"dayEndTime":"15:41","dayWorkTimeTotal":"7 ч 33 м "},{"monthDay":"14 АВГ","weekDay":"ПН","dayStartTime":"8:05","breaks":[{"breakStartTime":"8:16","breakEndTime":"8:25","breakTimeTotal":"9 м "},{"breakStartTime":"12:35","breakEndTime":"12:42","breakTimeTotal":"7 м "}],"dayEndTime":"15:59","dayWorkTimeTotal":"7 ч 38 м "},{"monthDay":"15 АВГ","weekDay":"ВТ","dayStartTime":"7:36","breaks":[{"breakStartTime":"7:45","breakEndTime":"7:56","breakTimeTotal":"11 м "},{"breakStartTime":"12:08","breakEndTime":"12:19","breakTimeTotal":"11 м "}],"dayEndTime":"15:51","dayWorkTimeTotal":"7 ч 52 м "},{"monthDay":"16 АВГ","weekDay":"СР","dayStartTime":"7:49","breaks":[{"breakStartTime":"8:07","breakEndTime":"8:20","breakTimeTotal":"13 м "},{"breakStartTime":"12:12","breakEndTime":"12:27","breakTimeTotal":"15 м "}],"dayEndTime":"16:21","dayWorkTimeTotal":"8 ч 4 м "},{"monthDay":"17 АВГ","weekDay":"ЧТ","dayStartTime":"7:15","breaks":[{"breakStartTime":"7:31","breakEndTime":"7:40","breakTimeTotal":"9 м "},{"breakStartTime":"12:06","breakEndTime":"12:24","breakTimeTotal":"18 м "}],"dayEndTime":"16:01","dayWorkTimeTotal":"8 ч 19 м "},{"monthDay":"18 АВГ","weekDay":"ПТ","dayStartTime":"7:46","breaks":[{"breakStartTime":"8:03","breakEndTime":"8:10","breakTimeTotal":"7 м "},{"breakStartTime":"13:22","breakEndTime":"13:31","breakTimeTotal":"9 м "}],"dayEndTime":"16:18","dayWorkTimeTotal":"8 ч 16 м "},{"monthDay":"21 АВГ","weekDay":"ПН","dayStartTime":"7:43","breaks":[{"breakStartTime":"7:54","breakEndTime":"8:04","breakTimeTotal":"10 м "},{"breakStartTime":"12:22","breakEndTime":"12:30","breakTimeTotal":"8 м "}],"dayEndTime":"16:08","dayWorkTimeTotal":"8 ч 7 м "},{"monthDay":"22 АВГ","weekDay":"ВТ","dayStartTime":"7:30","breaks":[{"breakStartTime":"7:46","breakEndTime":"7:55","breakTimeTotal":"9 м "},{"breakStartTime":"12:12","breakEndTime":"12:20","breakTimeTotal":"8 м "}],"dayEndTime":"16:15","dayWorkTimeTotal":"8 ч 28 м "},{"monthDay":"23 АВГ","weekDay":"СР","dayStartTime":"6:46","breaks":[{"breakStartTime":"7:40","breakEndTime":"7:49","breakTimeTotal":"9 м "},{"breakStartTime":"12:09","breakEndTime":"12:19","breakTimeTotal":"10 м "}],"dayEndTime":"15:39","dayWorkTimeTotal":"8 ч 33 м "},{"monthDay":"24 АВГ","weekDay":"ЧТ","dayStartTime":"7:43","breaks":[{"breakStartTime":"7:59","breakEndTime":"8:08","breakTimeTotal":"9 м "},{"breakStartTime":"10:51","breakEndTime":"12:26","breakTimeTotal":"1 ч 35 м "},{"breakStartTime":"12:39","breakEndTime":"12:45","breakTimeTotal":"6 м "}],"dayEndTime":"16:41","dayWorkTimeTotal":"7 ч 8 м "},{"monthDay":"25 АВГ","weekDay":"ПТ","dayStartTime":"7:56","breaks":[{"breakStartTime":"8:07","breakEndTime":"8:16","breakTimeTotal":"9 м "},{"breakStartTime":"12:07","breakEndTime":"12:08","breakTimeTotal":"1 м "},{"breakStartTime":"12:12","breakEndTime":"12:21","breakTimeTotal":"9 м "}],"dayEndTime":"16:32","dayWorkTimeTotal":"8 ч 17 м "},{"monthDay":"26 АВГ","weekDay":"СБ","dayStartTime":"14:22","dayEndTime":"15:26","dayWorkTimeTotal":"1 ч 4 м "},{"monthDay":"28 АВГ","weekDay":"ПН","dayStartTime":"7:41","breaks":[{"breakStartTime":"7:50","breakEndTime":"8:00","breakTimeTotal":"10 м "},{"breakStartTime":"11:57","breakEndTime":"12:05","breakTimeTotal":"8 м "}],"dayEndTime":"15:42","dayWorkTimeTotal":"7 ч 43 м "},{"monthDay":"29 АВГ","weekDay":"ВТ","dayStartTime":"7:31","breaks":[{"breakStartTime":"7:43","breakEndTime":"7:51","breakTimeTotal":"8 м "},{"breakStartTime":"12:11","breakEndTime":"12:19","breakTimeTotal":"8 м "}],"dayEndTime":"15:48","dayWorkTimeTotal":"8 ч 1 м "},{"monthDay":"30 АВГ","weekDay":"СР","dayStartTime":"7:43","breaks":[{"breakStartTime":"7:58","breakEndTime":"8:05","breakTimeTotal":"7 м "},{"breakStartTime":"12:20","breakEndTime":"12:28","breakTimeTotal":"8 м "}],"dayEndTime":"15:58","dayWorkTimeTotal":"8 ч 0 м "},{"monthDay":"31 АВГ","weekDay":"ЧТ","dayStartTime":"7:43","breaks":[{"breakStartTime":"7:54","breakEndTime":"8:04","breakTimeTotal":"10 м "},{"breakStartTime":"12:27","breakEndTime":"12:34","breakTimeTotal":"7 м "}],"dayEndTime":"15:56","dayWorkTimeTotal":"7 ч 56 м "},{"monthDay":"1 СЕН","weekDay":"ПТ","dayStartTime":"7:54","breaks":[{"breakStartTime":"8:02","breakEndTime":"8:12","breakTimeTotal":"10 м "},{"breakStartTime":"12:17","breakEndTime":"12:25","breakTimeTotal":"8 м "}],"dayEndTime":"15:43","dayWorkTimeTotal":"7 ч 31 м "},{"monthDay":"4 СЕН","weekDay":"ПН","dayStartTime":"7:27","breaks":[{"breakStartTime":"7:38","breakEndTime":"7:45","breakTimeTotal":"7 м "},{"breakStartTime":"12:14","breakEndTime":"12:20","breakTimeTotal":"6 м "}],"dayEndTime":"15:51","dayWorkTimeTotal":"8 ч 10 м "},{"monthDay":"5 СЕН","weekDay":"ВТ","dayStartTime":"7:36","breaks":[{"breakStartTime":"7:44","breakEndTime":"7:53","breakTimeTotal":"9 м "},{"breakStartTime":"12:01","breakEndTime":"12:09","breakTimeTotal":"8 м "}],"dayEndTime":"15:29","dayWorkTimeTotal":"7 ч 35 м "},{"monthDay":"6 СЕН","weekDay":"СР","dayStartTime":"7:45","breaks":[{"breakStartTime":"8:00","breakEndTime":"8:09","breakTimeTotal":"9 м "},{"breakStartTime":"12:05","breakEndTime":"12:11","breakTimeTotal":"6 м "}],"dayEndTime":"15:50","dayWorkTimeTotal":"7 ч 50 м "},{"monthDay":"7 СЕН","weekDay":"ЧТ","dayStartTime":"7:43","breaks":[{"breakStartTime":"7:54","breakEndTime":"8:02","breakTimeTotal":"8 м "},{"breakStartTime":"12:17","breakEndTime":"12:23","breakTimeTotal":"6 м "}],"dayEndTime":"15:59","dayWorkTimeTotal":"8 ч 2 м "},{"monthDay":"8 СЕН","weekDay":"ПТ","dayStartTime":"8:13","breaks":[{"breakStartTime":"8:25","breakEndTime":"8:33","breakTimeTotal":"8 м "},{"breakStartTime":"12:06","breakEndTime":"12:13","breakTimeTotal":"7 м "}],"dayEndTime":"15:53","dayWorkTimeTotal":"7 ч 25 м "},{"monthDay":"11 СЕН","weekDay":"ПН","dayStartTime":"7:53","breaks":[{"breakStartTime":"8:00","breakEndTime":"8:09","breakTimeTotal":"9 м "},{"breakStartTime":"12:00","breakEndTime":"12:07","breakTimeTotal":"7 м "}],"dayEndTime":"15:51","dayWorkTimeTotal":"7 ч 42 м "},{"monthDay":"12 СЕН","weekDay":"ВТ","dayStartTime":"7:35","breaks":[{"breakStartTime":"7:45","breakEndTime":"7:55","breakTimeTotal":"10 м "},{"breakStartTime":"12:22","breakEndTime":"12:30","breakTimeTotal":"8 м "}],"dayEndTime":"16:31","dayWorkTimeTotal":"8 ч 38 м "},{"monthDay":"13 СЕН","weekDay":"СР","dayStartTime":"7:36","breaks":[{"breakStartTime":"7:46","breakEndTime":"7:57","breakTimeTotal":"11 м "},{"breakStartTime":"12:19","breakEndTime":"12:25","breakTimeTotal":"6 м "},{"breakStartTime":"16:01","breakEndTime":"16:01","breakTimeTotal":"0 м "}],"dayEndTime":"16:01","dayWorkTimeTotal":"8 ч 8 м "},{"monthDay":"14 СЕН","weekDay":"ЧТ","dayStartTime":"7:55","breaks":[{"breakStartTime":"8:05","breakEndTime":"8:14","breakTimeTotal":"9 м "},{"breakStartTime":"12:13","breakEndTime":"12:20","breakTimeTotal":"7 м "}],"dayEndTime":"15:48","dayWorkTimeTotal":"7 ч 37 м "},{"monthDay":"15 СЕН","weekDay":"ПТ","dayStartTime":"7:51","breaks":[{"breakStartTime":"8:02","breakEndTime":"8:11","breakTimeTotal":"9 м "},{"breakStartTime":"12:16","breakEndTime":"12:23","breakTimeTotal":"7 м "}],"dayEndTime":"16:03","dayWorkTimeTotal":"7 ч 56 м "},{"monthDay":"18 СЕН","weekDay":"ПН","dayStartTime":"7:43","breaks":[{"breakStartTime":"7:54","breakEndTime":"8:04","breakTimeTotal":"10 м "},{"breakStartTime":"11:47","breakEndTime":"11:51","breakTimeTotal":"4 м "},{"breakStartTime":"11:54","breakEndTime":"11:58","breakTimeTotal":"4 м "}],"dayEndTime":"15:50","dayWorkTimeTotal":"7 ч 49 м "},{"monthDay":"19 СЕН","weekDay":"ВТ","dayStartTime":"7:37","breaks":[{"breakStartTime":"7:47","breakEndTime":"7:57","breakTimeTotal":"10 м "},{"breakStartTime":"12:08","breakEndTime":"12:14","breakTimeTotal":"6 м "}],"dayEndTime":"16:03","dayWorkTimeTotal":"8 ч 10 м "},{"monthDay":"20 СЕН","weekDay":"СР","dayStartTime":"7:35","breaks":[{"breakStartTime":"7:52","breakEndTime":"8:02","breakTimeTotal":"10 м "},{"breakStartTime":"12:31","breakEndTime":"12:38","breakTimeTotal":"7 м "}],"dayEndTime":"16:02","dayWorkTimeTotal":"8 ч 10 м "},{"monthDay":"21 СЕН","weekDay":"ЧТ","dayStartTime":"7:30","breaks":[{"breakStartTime":"7:42","breakEndTime":"7:52","breakTimeTotal":"10 м "},{"breakStartTime":"12:15","breakEndTime":"12:22","breakTimeTotal":"7 м "}],"dayEndTime":"16:02","dayWorkTimeTotal":"8 ч 14 м "},{"monthDay":"22 СЕН","weekDay":"ПТ","dayStartTime":"8:54","breaks":[{"breakStartTime":"12:27","breakEndTime":"12:34","breakTimeTotal":"7 м "}],"dayEndTime":"16:22","dayWorkTimeTotal":"7 ч 20 м "},{"monthDay":"25 СЕН","weekDay":"ПН","dayStartTime":"10:16","breaks":[{"breakStartTime":"12:08","breakEndTime":"12:16","breakTimeTotal":"8 м "}],"dayEndTime":"16:04","dayWorkTimeTotal":"5 ч 40 м "},{"monthDay":"26 СЕН","weekDay":"ВТ","dayStartTime":"11:50","breaks":[{"breakStartTime":"11:50","breakEndTime":"11:50","breakTimeTotal":"0 м "}],"dayEndTime":"11:50","dayWorkTimeTotal":"0 м "},{"monthDay":"27 СЕН","weekDay":"СР","dayStartTime":"7:36","breaks":[{"breakStartTime":"7:49","breakEndTime":"7:58","breakTimeTotal":"9 м "},{"breakStartTime":"12:08","breakEndTime":"12:18","breakTimeTotal":"10 м "}],"dayEndTime":"16:15","dayWorkTimeTotal":"8 ч 20 м "},{"monthDay":"28 СЕН","weekDay":"ЧТ","dayStartTime":"7:53","breaks":[{"breakStartTime":"8:04","breakEndTime":"8:12","breakTimeTotal":"8 м "},{"breakStartTime":"12:20","breakEndTime":"12:28","breakTimeTotal":"8 м "}],"dayEndTime":"15:57","dayWorkTimeTotal":"7 ч 48 м "},{"monthDay":"29 СЕН","weekDay":"ПТ","dayStartTime":"7:35","breaks":[{"breakStartTime":"7:45","breakEndTime":"7:56","breakTimeTotal":"11 м "},{"breakStartTime":"12:44","breakEndTime":"12:50","breakTimeTotal":"6 м "}],"dayEndTime":"16:28","dayWorkTimeTotal":"8 ч 36 м "},{"monthDay":"2 ОКТ","weekDay":"ПН","dayStartTime":"8:06","breaks":[{"breakStartTime":"8:17","breakEndTime":"8:26","breakTimeTotal":"9 м "},{"breakStartTime":"12:15","breakEndTime":"12:23","breakTimeTotal":"8 м "}],"dayEndTime":"15:58","dayWorkTimeTotal":"7 ч 35 м "},{"monthDay":"3 ОКТ","weekDay":"ВТ","dayStartTime":"7:12","breaks":[{"breakStartTime":"7:22","breakEndTime":"7:31","breakTimeTotal":"9 м "},{"breakStartTime":"12:02","breakEndTime":"12:10","breakTimeTotal":"8 м "}],"dayEndTime":"16:03","dayWorkTimeTotal":"8 ч 34 м "},{"monthDay":"4 ОКТ","weekDay":"СР","dayStartTime":"7:08","breaks":[{"breakStartTime":"7:17","breakEndTime":"7:27","breakTimeTotal":"10 м "},{"breakStartTime":"12:10","breakEndTime":"12:18","breakTimeTotal":"8 м "}],"dayEndTime":"16:11","dayWorkTimeTotal":"8 ч 45 м "},{"monthDay":"5 ОКТ","weekDay":"ЧТ","dayStartTime":"7:07","breaks":[{"breakStartTime":"7:22","breakEndTime":"7:30","breakTimeTotal":"8 м "},{"breakStartTime":"12:10","breakEndTime":"12:17","breakTimeTotal":"7 м "}],"dayEndTime":"16:24","dayWorkTimeTotal":"9 ч 1 м "},{"monthDay":"6 ОКТ","weekDay":"ПТ","dayStartTime":"7:10","breaks":[{"breakStartTime":"7:21","breakEndTime":"7:29","breakTimeTotal":"8 м "},{"breakStartTime":"12:15","breakEndTime":"12:22","breakTimeTotal":"7 м "}],"dayEndTime":"15:56","dayWorkTimeTotal":"8 ч 30 м "},{"monthDay":"9 ОКТ","weekDay":"ПН","dayStartTime":"7:48","breaks":[{"breakStartTime":"8:02","breakEndTime":"8:10","breakTimeTotal":"8 м "},{"breakStartTime":"12:07","breakEndTime":"12:14","breakTimeTotal":"7 м "}],"dayEndTime":"16:02","dayWorkTimeTotal":"7 ч 58 м "},{"monthDay":"10 ОКТ","weekDay":"ВТ","dayStartTime":"7:15","breaks":[{"breakStartTime":"7:26","breakEndTime":"7:35","breakTimeTotal":"9 м "},{"breakStartTime":"12:46","breakEndTime":"12:53","breakTimeTotal":"7 м "}],"dayEndTime":"16:04","dayWorkTimeTotal":"8 ч 33 м "},{"monthDay":"11 ОКТ","weekDay":"СР","dayStartTime":"7:28","breaks":[{"breakStartTime":"7:37","breakEndTime":"7:46","breakTimeTotal":"9 м "},{"breakStartTime":"12:08","breakEndTime":"12:18","breakTimeTotal":"10 м "}],"dayEndTime":"16:03","dayWorkTimeTotal":"8 ч 16 м "},{"monthDay":"12 ОКТ","weekDay":"ЧТ","dayStartTime":"7:06","breaks":[{"breakStartTime":"7:16","breakEndTime":"7:28","breakTimeTotal":"12 м "},{"breakStartTime":"12:15"}],"dayEndTime":"15:32","dayWorkTimeTotal":"8 ч 14 м "},{"monthDay":"13 ОКТ","weekDay":"ПТ","dayStartTime":"7:22","breaks":[{"breakStartTime":"7:34","breakEndTime":"7:45","breakTimeTotal":"11 м "},{"breakStartTime":"12:09","breakEndTime":"12:16","breakTimeTotal":"7 м "}],"dayEndTime":"15:43","dayWorkTimeTotal":"8 ч 3 м "},{"monthDay":"16 ОКТ","weekDay":"ПН","dayStartTime":"7:00","dayEndTime":"7:00","dayWorkTimeTotal":"0 м "},{"monthDay":"17 ОКТ","weekDay":"ВТ","dayStartTime":"7:00","breaks":[{"breakStartTime":"7:11","breakEndTime":"7:25","breakTimeTotal":"14 м "},{"breakStartTime":"12:12","breakEndTime":"12:26","breakTimeTotal":"12 м "}],"dayEndTime":"16:38","dayWorkTimeTotal":"9 ч 12 м "},{"monthDay":"18 ОКТ","weekDay":"СР","dayStartTime":"6:54","breaks":[{"breakStartTime":"7:08","breakEndTime":"7:17","breakTimeTotal":"9 м "},{"breakStartTime":"12:02","breakEndTime":"12:16","breakTimeTotal":"14 м "}],"dayEndTime":"16:44","dayWorkTimeTotal":"9 ч 27 м "},{"monthDay":"19 ОКТ","weekDay":"ЧТ","dayStartTime":"7:02","breaks":[{"breakStartTime":"7:15","breakEndTime":"7:22","breakTimeTotal":"7 м "},{"breakStartTime":"12:04","breakEndTime":"12:18","breakTimeTotal":"14 м "}],"dayEndTime":"16:23","dayWorkTimeTotal":"9 ч 0 м "},{"monthDay":"20 ОКТ","weekDay":"ПТ","dayStartTime":"7:00","breaks":[{"breakStartTime":"7:11","breakEndTime":"7:19","breakTimeTotal":"8 м "},{"breakStartTime":"12:05","breakEndTime":"12:12","breakTimeTotal":"7 м "}],"dayEndTime":"16:32","dayWorkTimeTotal":"9 ч 16 м "},{"monthDay":"23 ОКТ","weekDay":"ПН","dayStartTime":"7:15","breaks":[{"breakStartTime":"7:28","breakEndTime":"7:38","breakTimeTotal":"10 м "},{"breakStartTime":"11:53","breakEndTime":"12:04","breakTimeTotal":"11 м "}],"dayEndTime":"15:24","dayWorkTimeTotal":"7 ч 48 м "},{"monthDay":"24 ОКТ","weekDay":"ВТ","dayStartTime":"7:10","breaks":[{"breakStartTime":"7:21","breakEndTime":"7:32","breakTimeTotal":"11 м "},{"breakStartTime":"12:01","breakEndTime":"12:09","breakTimeTotal":"8 м "}],"dayEndTime":"16:15","dayWorkTimeTotal":"8 ч 45 м "},{"monthDay":"25 ОКТ","weekDay":"СР","dayStartTime":"7:09","breaks":[{"breakStartTime":"7:20","breakEndTime":"7:29","breakTimeTotal":"9 м "},{"breakStartTime":"12:07","breakEndTime":"12:13","breakTimeTotal":"6 м "}],"dayEndTime":"16:07","dayWorkTimeTotal":"8 ч 43 м "},{"monthDay":"26 ОКТ","weekDay":"ЧТ","dayStartTime":"7:02","breaks":[{"breakStartTime":"7:19","breakEndTime":"7:29","breakTimeTotal":"10 м "},{"breakStartTime":"11:43","breakEndTime":"12:01","breakTimeTotal":"18 м "}],"dayEndTime":"16:01","dayWorkTimeTotal":"8 ч 30 м "},{"monthDay":"27 ОКТ","weekDay":"ПТ","dayStartTime":"7:04","breaks":[{"breakStartTime":"7:16","breakEndTime":"7:25","breakTimeTotal":"9 м "},{"breakStartTime":"11:47","breakEndTime":"12:02","breakTimeTotal":"15 м "}],"dayEndTime":"16:40","dayWorkTimeTotal":"9 ч 12 м "},{"monthDay":"30 ОКТ","weekDay":"ПН","dayStartTime":"7:04","breaks":[{"breakStartTime":"7:20","breakEndTime":"7:28","breakTimeTotal":"8 м "},{"breakStartTime":"12:28","breakEndTime":"12:36","breakTimeTotal":"8 м "}],"dayEndTime":"15:56","dayWorkTimeTotal":"8 ч 36 м "},{"monthDay":"31 ОКТ","weekDay":"ВТ","dayStartTime":"7:10","breaks":[{"breakStartTime":"7:21","breakEndTime":"7:30","breakTimeTotal":"9 м "},{"breakStartTime":"8:58","breakEndTime":"11:50","breakTimeTotal":"2 ч 52 м "}],"dayEndTime":"16:07","dayWorkTimeTotal":"5 ч 56 м "},{"monthDay":"1 НОЯ","weekDay":"СР","dayStartTime":"7:15","breaks":[{"breakStartTime":"7:27","breakEndTime":"7:36","breakTimeTotal":"9 м "},{"breakStartTime":"12:03","breakEndTime":"12:11","breakTimeTotal":"8 м "}],"dayEndTime":"15:47","dayWorkTimeTotal":"8 ч 14 м "},{"monthDay":"2 НОЯ","weekDay":"ЧТ","dayStartTime":"7:04","breaks":[{"breakStartTime":"7:18","breakEndTime":"7:29","breakTimeTotal":"11 м "},{"breakStartTime":"12:31","breakEndTime":"12:37","breakTimeTotal":"6 м "}],"dayEndTime":"15:53","dayWorkTimeTotal":"8 ч 32 м "},{"monthDay":"3 НОЯ","weekDay":"ПТ","dayStartTime":"7:00","breaks":[{"breakStartTime":"7:11","breakEndTime":"7:20","breakTimeTotal":"9 м "},{"breakStartTime":"12:14","breakEndTime":"12:22","breakTimeTotal":"8 м "}],"dayEndTime":"16:04","dayWorkTimeTotal":"8 ч 46 м "},{"monthDay":"6 НОЯ","weekDay":"ПН","dayStartTime":"7:11","breaks":[{"breakStartTime":"7:24","breakEndTime":"7:31","breakTimeTotal":"7 м "},{"breakStartTime":"12:00","breakEndTime":"12:09","breakTimeTotal":"9 м "}],"dayEndTime":"15:58","dayWorkTimeTotal":"8 ч 30 м "},{"monthDay":"7 НОЯ","weekDay":"ВТ","dayStartTime":"7:05","breaks":[{"breakStartTime":"7:19","breakEndTime":"7:27","breakTimeTotal":"8 м "},{"breakStartTime":"12:00","breakEndTime":"12:07","breakTimeTotal":"7 м "}],"dayEndTime":"15:26","dayWorkTimeTotal":"8 ч 5 м "},{"monthDay":"8 НОЯ","weekDay":"СР","dayStartTime":"7:33","breaks":[{"breakStartTime":"7:46","breakEndTime":"7:54","breakTimeTotal":"8 м "},{"breakEndTime":"7:54","breakTimeTotal":"8 м "}],"dayEndTime":"16:01","dayWorkTimeTotal":"8 ч 20 м "},{"monthDay":"9 НОЯ","weekDay":"ЧТ","dayStartTime":"7:10","breaks":[{"breakStartTime":"7:20","breakEndTime":"7:31","breakTimeTotal":"11 м "},{"breakStartTime":"12:15","breakEndTime":"12:22","breakTimeTotal":"7 м "}],"dayEndTime":"15:47","dayWorkTimeTotal":"8 ч 18 м "},{"monthDay":"10 НОЯ","weekDay":"ПТ","dayStartTime":"7:02","breaks":[{"breakStartTime":"7:17","breakEndTime":"7:30","breakTimeTotal":"13 м "},{"breakStartTime":"12:13","breakEndTime":"12:24","breakTimeTotal":"11 м "}],"dayEndTime":"16:44","dayWorkTimeTotal":"9 ч 18 м "},{"monthDay":"13 НОЯ","weekDay":"ПН","dayStartTime":"7:16","breaks":[{"breakStartTime":"7:29","breakEndTime":"7:39","breakTimeTotal":"10 м "},{"breakStartTime":"12:27","breakEndTime":"12:35","breakTimeTotal":"8 м "}],"dayEndTime":"16:30","dayWorkTimeTotal":"8 ч 56 м "},{"monthDay":"14 НОЯ","weekDay":"ВТ","dayStartTime":"7:00","breaks":[{"breakStartTime":"7:13","breakEndTime":"7:23","breakTimeTotal":"10 м "},{"breakStartTime":"12:14","breakEndTime":"12:23","breakTimeTotal":"9 м "}],"dayEndTime":"16:40","dayWorkTimeTotal":"9 ч 20 м "},{"monthDay":"15 НОЯ","weekDay":"СР","dayStartTime":"7:02","breaks":[{"breakStartTime":"7:14","breakEndTime":"7:24","breakTimeTotal":"10 м "},{"breakStartTime":"12:11","breakEndTime":"12:18","breakTimeTotal":"7 м "}],"dayEndTime":"16:41","dayWorkTimeTotal":"9 ч 21 м "},{"monthDay":"16 НОЯ","weekDay":"ЧТ","dayStartTime":"7:00","breaks":[{"breakStartTime":"7:14","breakEndTime":"7:25","breakTimeTotal":"11 м "},{"breakStartTime":"12:07","breakEndTime":"12:16","breakTimeTotal":"9 м "}],"dayEndTime":"16:11","dayWorkTimeTotal":"8 ч 50 м "},{"monthDay":"17 НОЯ","weekDay":"ПТ","dayStartTime":"7:14","breaks":[{"breakStartTime":"7:27","breakEndTime":"7:36","breakTimeTotal":"9 м "},{"breakStartTime":"11:58","breakEndTime":"12:06","breakTimeTotal":"8 м "}],"dayEndTime":"17:07","dayWorkTimeTotal":"9 ч 36 м "},{"monthDay":"20 НОЯ","weekDay":"ПН","dayStartTime":"8:11","breaks":[{"breakStartTime":"8:29","breakEndTime":"8:37","breakTimeTotal":"8 м "},{"breakStartTime":"12:00","breakEndTime":"12:06","breakTimeTotal":"6 м "}],"dayEndTime":"16:01","dayWorkTimeTotal":"7 ч 36 м "},{"monthDay":"21 НОЯ","weekDay":"ВТ","dayStartTime":"7:06","breaks":[{"breakStartTime":"7:19","breakEndTime":"7:28","breakTimeTotal":"9 м "},{"breakEndTime":"7:28","breakTimeTotal":"9 м "}],"dayEndTime":"16:08","dayWorkTimeTotal":"8 ч 53 м "},{"monthDay":"22 НОЯ","weekDay":"СР","dayStartTime":"7:14","breaks":[{"breakStartTime":"7:27","breakEndTime":"7:35","breakTimeTotal":"8 м "},{"breakStartTime":"12:24","breakEndTime":"12:33","breakTimeTotal":"9 м "}],"dayEndTime":"16:05","dayWorkTimeTotal":"8 ч 33 м "},{"monthDay":"23 НОЯ","weekDay":"ЧТ","dayStartTime":"7:23","breaks":[{"breakStartTime":"7:36","breakEndTime":"7:45","breakTimeTotal":"9 м "},{"breakStartTime":"12:03","breakEndTime":"12:12","breakTimeTotal":"9 м "}],"dayEndTime":"15:58","dayWorkTimeTotal":"8 ч 17 м "},{"monthDay":"24 НОЯ","weekDay":"ПТ","dayStartTime":"7:35","breaks":[{"breakStartTime":"7:53","breakEndTime":"8:06","breakTimeTotal":"13 м "},{"breakStartTime":"12:07","breakEndTime":"12:18","breakTimeTotal":"11 м "}],"dayEndTime":"16:11","dayWorkTimeTotal":"8 ч 11 м "},{"monthDay":"27 НОЯ","weekDay":"ПН","dayStartTime":"7:17","breaks":[{"breakStartTime":"7:28","breakEndTime":"7:38","breakTimeTotal":"10 м "},{"breakStartTime":"12:06","breakEndTime":"12:15","breakTimeTotal":"9 м "}],"dayEndTime":"15:37","dayWorkTimeTotal":"8 ч 0 м "},{"monthDay":"28 НОЯ","weekDay":"ВТ","dayStartTime":"7:41","breaks":[{"breakStartTime":"7:55","breakEndTime":"8:04","breakTimeTotal":"9 м "},{"breakStartTime":"12:06","breakEndTime":"12:12","breakTimeTotal":"6 м "}],"dayEndTime":"16:05","dayWorkTimeTotal":"8 ч 9 м "},{"monthDay":"29 НОЯ","weekDay":"СР","dayStartTime":"7:44","breaks":[{"breakStartTime":"8:01","breakEndTime":"8:07","breakTimeTotal":"6 м "},{"breakStartTime":"8:10","breakEndTime":"8:14","breakTimeTotal":"4 м "},{"breakStartTime":"12:03","breakEndTime":"12:10","breakTimeTotal":"7 м "}],"dayEndTime":"15:30","dayWorkTimeTotal":"7 ч 28 м "},{"monthDay":"30 НОЯ","weekDay":"ЧТ","dayStartTime":"7:29","breaks":[{"breakStartTime":"7:39","breakEndTime":"7:53","breakTimeTotal":"14 м "},{"breakStartTime":"12:11","breakEndTime":"12:18","breakTimeTotal":"7 м "}],"dayEndTime":"15:29","dayWorkTimeTotal":"7 ч 39 м "},{"monthDay":"1 ДЕК","weekDay":"ПТ","dayStartTime":"7:26","breaks":[{"breakStartTime":"7:40","breakEndTime":"7:51","breakTimeTotal":"11 м "},{"breakStartTime":"12:28","breakEndTime":"12:35","breakTimeTotal":"7 м "}],"dayEndTime":"15:12","dayWorkTimeTotal":"7 ч 28 м "},{"monthDay":"4 ДЕК","weekDay":"ПН","dayStartTime":"8:07","breaks":[{"breakStartTime":"8:18","breakEndTime":"8:29","breakTimeTotal":"11 м "},{"breakStartTime":"12:47","breakEndTime":"12:53","breakTimeTotal":"6 м "}],"dayEndTime":"16:11","dayWorkTimeTotal":"7 ч 47 м "},{"monthDay":"5 ДЕК","weekDay":"ВТ","dayStartTime":"7:05","breaks":[{"breakStartTime":"7:26","breakEndTime":"7:34","breakTimeTotal":"8 м "},{"breakStartTime":"12:24","breakEndTime":"12:31","breakTimeTotal":"7 м "}],"dayEndTime":"15:29","dayWorkTimeTotal":"8 ч 8 м "},{"monthDay":"6 ДЕК","weekDay":"СР","dayStartTime":"7:05","breaks":[{"breakStartTime":"7:17","breakEndTime":"7:27","breakTimeTotal":"10 м "},{"breakStartTime":"12:05","breakEndTime":"12:12","breakTimeTotal":"7 м "}],"dayEndTime":"14:56","dayWorkTimeTotal":"7 ч 34 м "},{"monthDay":"7 ДЕК","weekDay":"ЧТ","dayStartTime":"7:42","dayEndTime":"15:35","dayWorkTimeTotal":"7 ч 53 м "},{"monthDay":"8 ДЕК","weekDay":"ПТ","dayStartTime":"7:27","dayEndTime":"16:17","dayWorkTimeTotal":"8 ч 49 м "},{"monthDay":"11 ДЕК","weekDay":"ПН","dayStartTime":"7:40","dayEndTime":"15:36","dayWorkTimeTotal":"7 ч 55 м "},{"monthDay":"12 ДЕК","weekDay":"ВТ","dayStartTime":"7:01","dayEndTime":"14:40","dayWorkTimeTotal":"7 ч 38 м "},{"monthDay":"13 ДЕК","weekDay":"СР","dayStartTime":"7:01","dayEndTime":"15:37","dayWorkTimeTotal":"8 ч 35 м "},{"monthDay":"14 ДЕК","weekDay":"ЧТ","dayStartTime":"7:00","dayEndTime":"15:08","dayWorkTimeTotal":"8 ч 8 м "},{"monthDay":"15 ДЕК","weekDay":"ПТ","dayStartTime":"7:09","dayEndTime":"15:11","dayWorkTimeTotal":"8 ч 2 м "},{"monthDay":"18 ДЕК","weekDay":"ПН","dayStartTime":"7:09","dayEndTime":"15:41","dayWorkTimeTotal":"8 ч 32 м "},{"monthDay":"19 ДЕК","weekDay":"ВТ","dayStartTime":"7:15","dayEndTime":"15:22","dayWorkTimeTotal":"8 ч 7 м "},{"monthDay":"20 ДЕК","weekDay":"СР","dayStartTime":"7:09","dayEndTime":"15:25","dayWorkTimeTotal":"8 ч 16 м "},{"monthDay":"21 ДЕК","weekDay":"ЧТ","dayStartTime":"7:21","dayEndTime":"15:40","dayWorkTimeTotal":"8 ч 18 м "},{"monthDay":"22 ДЕК","weekDay":"ПТ","dayStartTime":"7:04","dayEndTime":"15:22","dayWorkTimeTotal":"8 ч 17 м "},{"monthDay":"23 ДЕК","weekDay":"СБ","dayStartTime":"7:04","dayEndTime":"11:16","dayWorkTimeTotal":"4 ч 11 м "},{"monthDay":"25 ДЕК","weekDay":"ПН","dayStartTime":"7:04","dayEndTime":"15:25","dayWorkTimeTotal":"8 ч 21 м "},{"monthDay":"26 ДЕК","weekDay":"ВТ","dayStartTime":"7:01","dayEndTime":"16:11","dayWorkTimeTotal":"9 ч 10 м "},{"monthDay":"27 ДЕК","weekDay":"СР","dayStartTime":"6:59","breaks":[{"breakStartTime":"16:24","breakEndTime":"16:24","breakTimeTotal":"0 м "}],"dayEndTime":"16:24","dayWorkTimeTotal":"9 ч 25 м "},{"monthDay":"28 ДЕК","weekDay":"ЧТ","dayStartTime":"6:51","dayEndTime":"15:53","dayWorkTimeTotal":"9 ч 1 м "},{"monthDay":"29 ДЕК","weekDay":"ПТ","dayStartTime":"7:02","dayEndTime":"16:22","dayWorkTimeTotal":"9 ч 20 м "},{"monthDay":"8 ЯНВ","weekDay":"ПН","dayStartTime":"8:46","dayEndTime":"16:45","dayWorkTimeTotal":"7 ч 58 м "},{"monthDay":"9 ЯНВ","weekDay":"ВТ","dayStartTime":"7:52","dayEndTime":"16:12","dayWorkTimeTotal":"8 ч 20 м "},{"monthDay":"10 ЯНВ","weekDay":"СР","dayStartTime":"6:54","dayEndTime":"16:00","dayWorkTimeTotal":"9 ч 5 м "},{"monthDay":"11 ЯНВ","weekDay":"ЧТ","dayStartTime":"7:13","dayEndTime":"15:52","dayWorkTimeTotal":"8 ч 39 м "},{"monthDay":"12 ЯНВ","weekDay":"ПТ","dayStartTime":"7:23","dayEndTime":"15:39","dayWorkTimeTotal":"8 ч 16 м "},{"monthDay":"15 ЯНВ","weekDay":"ПН","dayStartTime":"7:10","dayEndTime":"15:53","dayWorkTimeTotal":"8 ч 42 м "},{"monthDay":"16 ЯНВ","weekDay":"ВТ","dayStartTime":"7:50","breaks":[{"breakStartTime":"15:59","breakEndTime":"15:59","breakTimeTotal":"0 м "}],"dayEndTime":"15:59","dayWorkTimeTotal":"8 ч 9 м "},{"monthDay":"17 ЯНВ","weekDay":"СР","dayStartTime":"7:03","dayEndTime":"15:35","dayWorkTimeTotal":"8 ч 32 м "},{"monthDay":"18 ЯНВ","weekDay":"ЧТ","dayStartTime":"6:52"}]}